pytorch_functional/__init__.py
pytorch_functional/examples/__init__.py
pytorch_functional/examples/encoder_decoder.py
pytorch_functional/examples/resnet.py
pytorch_functional/examples/vgg.py
pytorch_functional/src/__init__.py
pytorch_functional/src/functional_model.py
pytorch_functional/src/layers.py
pytorch_functional/src/tools.py
pytorch_functional/src/training_tools.py
pytorch_functional-0.1.0.dist-info/LICENSE
pytorch_functional-0.1.0.dist-info/METADATA
pytorch_functional-0.1.0.dist-info/WHEEL
pytorch_functional-0.1.0.dist-info/top_level.txt
pytorch_functional-0.1.0.dist-info/RECORD
