Metadata-Version: 2.1
Name: pytorch-functional
Version: 0.1.0
Summary: Provides functional API for model creation in PyTorch
Home-page: https://github.com/gahaalt/pytorch-functional-api
Author: gahaalt
Author-email: gahaalt@gmail.com
License: UNKNOWN
Platform: UNKNOWN
Classifier: Programming Language :: Python :: 3
Classifier: License :: OSI Approved :: MIT License
Classifier: Operating System :: OS Independent
Requires-Python: >=3.6
